{
  "version": "0.3.14-fixed",
  "steps": [
    {
      "tag": "CreateField",
      "model": "Clinic",
      "field": "urgentPrice",
      "type": "Int",
      "arity": "Required"
    },
    {
      "tag": "CreateDirective",
      "location": {
        "path": {
          "tag": "Field",
          "model": "Clinic",
          "field": "urgentPrice"
        },
        "directive": "default"
      }
    },
    {
      "tag": "CreateArgument",
      "location": {
        "tag": "Directive",
        "path": {
          "tag": "Field",
          "model": "Clinic",
          "field": "urgentPrice"
        },
        "directive": "default"
      },
      "argument": "",
      "value": "0"
    },
    {
      "tag": "UpdateArgument",
      "location": {
        "tag": "Directive",
        "path": {
          "tag": "Field",
          "model": "Clinic",
          "field": "examinationPrice"
        },
        "directive": "default"
      },
      "argument": "",
      "newValue": "0"
    },
    {
      "tag": "UpdateArgument",
      "location": {
        "tag": "Directive",
        "path": {
          "tag": "Field",
          "model": "Clinic",
          "field": "followupPrice"
        },
        "directive": "default"
      },
      "argument": "",
      "newValue": "0"
    },
    {
      "tag": "UpdateArgument",
      "location": {
        "tag": "Directive",
        "path": {
          "tag": "Field",
          "model": "Clinic",
          "field": "duration"
        },
        "directive": "default"
      },
      "argument": "",
      "newValue": "5"
    }
  ]
}